clientele/__init__.py
clientele/cli.py
clientele/mypy.py
clientele/py.typed
clientele/settings.py
clientele/testing.py
clientele/utils.py
clientele/api/__init__.py
clientele/api/client.py
clientele/api/config.py
clientele/api/exceptions.py
clientele/api/requests.py
clientele/api/type_utils.py
clientele/api/stream/__init__.py
clientele/api/stream/parser.py
clientele/cache/__init__.py
clientele/cache/backends.py
clientele/cache/decorator.py
clientele/cache/key_generator.py
clientele/cache/types.py
clientele/generators/README.md
clientele/generators/__init__.py
clientele/generators/base.py
clientele/generators/base_clients.py
clientele/generators/base_http.py
clientele/generators/cicerone_compat.py
clientele/generators/schema_utils.py
clientele/generators/api/__init__.py
clientele/generators/api/generator.py
clientele/generators/api/writer.py
clientele/generators/api/generators/__init__.py
clientele/generators/api/generators/clients.py
clientele/generators/api/generators/schemas.py
clientele/generators/api/templates/api_get_method.jinja2
clientele/generators/api/templates/api_post_method.jinja2
clientele/generators/api/templates/client_py.jinja2
clientele/generators/api/templates/config_py.jinja2
clientele/generators/api/templates/manifest.jinja2
clientele/generators/api/templates/pyproject.toml.jinja2
clientele/generators/api/templates/schema_class.jinja2
clientele/generators/api/templates/schema_helpers.jinja2
clientele/generators/api/templates/schema_type_alias.jinja2
clientele/generators/api/templates/schemas_py.jinja2
clientele/generators/basic/__init__.py
clientele/generators/basic/generator.py
clientele/generators/basic/writer.py
clientele/generators/basic/templates/client_py.jinja2
clientele/generators/basic/templates/config_py.jinja2
clientele/generators/basic/templates/manifest.jinja2
clientele/generators/basic/templates/schemas_py.jinja2
clientele/generators/standard/__init__.py
clientele/generators/standard/generator.py
clientele-1.11.0.dist-info/METADATA
clientele-1.11.0.dist-info/WHEEL
clientele-1.11.0.dist-info/entry_points.txt
clientele-1.11.0.dist-info/licenses/LICENSE
clientele-1.11.0.dist-info/RECORD
