Metadata-Version: 2.4
Name: clientele
Version: 1.11.0
Summary: Clientele is a different way to build Python API Clients
Project-URL: Homepage, https://clientele.dev
Project-URL: Changelog, https://docs.clientele.dev/CHANGELOG/
Project-URL: Documentation, https://docs.clientele.dev/
Project-URL: Issues, https://github.com/phalt/clientele/issues
Author-email: Paul Hallett <paulandrewhallett@gmail.com>
License: MIT
License-File: LICENSE
Requires-Python: >=3.10
Requires-Dist: cicerone==0.3.0
Requires-Dist: click>=8.3.1
Requires-Dist: httpx>=0.28.1
Requires-Dist: jinja2>=3.1.6
Requires-Dist: pydantic-settings>=2.12.0
Requires-Dist: pydantic>=2.12.5
Requires-Dist: pyyaml>=6.0.3
Requires-Dist: rich>=14.2.0
Requires-Dist: ruff>=0.14.10
Requires-Dist: stamina>=25.2.0
Requires-Dist: types-pyyaml>=6.0.12.20250915
